mangoapi/__init__.py
mangoapi/base_site.py
mangoapi/exceptions.py
mangoapi/mangadex.py
mangoapi/mangasee.py
mangoapi/weebcentral.py
pytaku/__init__.py
pytaku/conf.py
pytaku/database/common.py
pytaku/database/migrations/__init__.py
pytaku/database/migrations/latest_schema.sql
pytaku/database/migrations/m0001.sql
pytaku/database/migrations/m0002.sql
pytaku/database/migrations/m0003.sql
pytaku/database/migrations/m0004.sql
pytaku/database/migrations/m0005.sql
pytaku/database/migrations/m0006.sql
pytaku/database/migrations/m0007.sql
pytaku/database/migrations/m0008.sql
pytaku/database/migrations/m0009.sql
pytaku/database/migrator.py
pytaku/decorators.py
pytaku/js-src/layout.js
pytaku/js-src/main.js
pytaku/js-src/models.js
pytaku/js-src/routes/authentication.js
pytaku/js-src/routes/chapter.js
pytaku/js-src/routes/follows.js
pytaku/js-src/routes/home.js
pytaku/js-src/routes/importer.js
pytaku/js-src/routes/search.js
pytaku/js-src/routes/title.js
pytaku/js-src/utils.js
pytaku/main.py
pytaku/persistence.py
pytaku/scheduler.py
pytaku/scripts/__init__.py
pytaku/scripts/migrate_mangasee_chapter_ids.py
pytaku/source_sites.py
pytaku/static/darkmode.css
pytaku/static/favicon.png
pytaku/static/favicon.svg
pytaku/static/feathericons/LICENSES
pytaku/static/feathericons/font.ttf
pytaku/static/feathericons/font.woff
pytaku/static/feathericons/iconfont.css
pytaku/static/js/main.min.js
pytaku/static/js/main.min.js.map
pytaku/static/lookandfeel.css
pytaku/static/minireset.css
pytaku/static/pytaku.svg
pytaku/static/spa.css
pytaku/static/vendored/mithril.min.js
pytaku/storages.py
pytaku/templates/error.html
pytaku/templates/spa.html
pytaku-0.8.2.dist-info/LICENSE
pytaku-0.8.2.dist-info/METADATA
pytaku-0.8.2.dist-info/WHEEL
pytaku-0.8.2.dist-info/entry_points.txt
pytaku-0.8.2.dist-info/RECORD
