Metadata-Version: 2.3
Name: pytaku
Version: 0.8.2
Summary: Self-hostable web-based manga reader
License: AGPL-3.0-only
Requires-Python: >=3.11
Classifier: License :: OSI Approved :: GNU Affero General Public License v3
Classifier: Programming Language :: Python :: 3
Classifier: Programming Language :: Python :: 3.11
Classifier: Programming Language :: Python :: 3.12
Classifier: Programming Language :: Python :: 3.13
Requires-Dist: apsw (>=3.49.1.0)
Requires-Dist: argon2-cffi (>=23.1.0)
Requires-Dist: bbcode (>=1.1.0)
Requires-Dist: flask (>=3.1.0)
Requires-Dist: goodconf (>=6.1.2)
Requires-Dist: gunicorn (>=23.0.0)
Requires-Dist: requests (>=2.32.3)
